setup.py
distributions/Binomialdistribution.py
distributions/Gaussiandistribution.py
distributions/Generaldistribution.py
distributions/__init__.py
ka_distributions.egg-info/PKG-INFO
ka_distributions.egg-info/SOURCES.txt
ka_distributions.egg-info/dependency_links.txt
ka_distributions.egg-info/not-zip-safe
ka_distributions.egg-info/top_level.txt